seedr_client/__init__.py
seedr_client/errors.py
seedr_client/seedr_handler.py
seedr_client-0.1.0.dist-info/METADATA
seedr_client-0.1.0.dist-info/WHEEL
seedr_client-0.1.0.dist-info/top_level.txt
seedr_client-0.1.0.dist-info/RECORD
